<Properties StartupConfiguration="{7A6F53FB-0BC4-4B13-A50E-C9813BBD2812}|Default">
  <MonoDevelop.Ide.Workbench ActiveDocument="Cauldron/OneSprite.cs">
    <Files>
      <File FileName="Cauldron/MainPage.xaml.cs" Line="34" Column="11" />
      <File FileName="Cauldron/Tools.cs" Line="59" Column="15" />
      <File FileName="Cauldron/Tiled.cs" Line="63" Column="19" />
      <File FileName="Cauldron.MacOS/AppDelegate.cs" Line="17" Column="101" />
      <File FileName="Cauldron/OneSprite.cs" Line="13" Column="9" />
    </Files>
  </MonoDevelop.Ide.Workbench>
  <MonoDevelop.Ide.Workspace ActiveConfiguration="Debug" />
  <MonoDevelop.Ide.DebuggingService.Breakpoints>
    <BreakpointStore />
  </MonoDevelop.Ide.DebuggingService.Breakpoints>
  <MonoDevelop.Ide.ItemProperties.Cauldron.Android PreferredExecutionTarget="Android.Mon4.4nexus" FirstBuild="True" />
  <MonoDevelop.Ide.DebuggingService.PinnedWatches />
  <MonoDevelop.Ide.ItemProperties.Cauldron.MacOS PreferredExecutionTarget="Test1" />
  <MonoDevelop.Ide.ItemProperties.Cauldron.iOS PreferredExecutionTarget="MonoDevelop.IPhone.IPhoneSimulatorTarget.812D8BFA-8F11-4213-BCF5-0F7B02470B12" />
  <MultiItemStartupConfigurations />
</Properties>